openbb_fd/__init__.py
openbb_fd/models/__init__.py
openbb_fd/models/crypto_search.py
openbb_fd/models/equity_search.py
openbb_fd/models/etf_search.py
openbb_fd/utils/__init__.py
openbb_fd/utils/helpers.py
openbb_fd-1.0.0.dist-info/LICENSE
openbb_fd-1.0.0.dist-info/METADATA
openbb_fd-1.0.0.dist-info/WHEEL
openbb_fd-1.0.0.dist-info/entry_points.txt
openbb_fd-1.0.0.dist-info/RECORD
