Metadata-Version: 2.1
Name: openbb-fd
Version: 1.0.0
Summary: Integration of Jeroen Bouma's Finance Database with OpenBB
Author: piiq
Author-email: piiq@tinag.ru
Requires-Python: >=3.8,<3.12
Classifier: Programming Language :: Python :: 3
Classifier: Programming Language :: Python :: 3.8
Classifier: Programming Language :: Python :: 3.9
Classifier: Programming Language :: Python :: 3.10
Classifier: Programming Language :: Python :: 3.11
Requires-Dist: openbb-core (>=1.0.1,<2.0.0)
